{
  "objects": [
    {
      "color_name": "purple",
      "size_name": "small",
      "mat_name": "metal",
      "obj_name": "sphere",
      "motion_name": "bouncing"
    },
    {
      "color_name": "brown",
      "size_name": "small",
      "mat_name": "metal",
      "obj_name": "cube",
      "motion_name": "still"
    },
    {
      "color_name": "blue",
      "size_name": "large",
      "mat_name": "rubber",
      "obj_name": "cube",
      "motion_name": "spinning"
    }
  ],
  "description": [
    "There are a small sphere of purple color and shiny texture, a small cube of brown color and shiny texture and a large cube of blue color and matte texture."
  ],
  "source": [
    "CLEVR_valA_004290.png"
  ]
}